{
    "code": "GIE.horario2425",
    "name": "Ingeniería Eléctrica",
    "subjects": [
        {
            "code": "21718001"
        },
        {
            "code": "21718002"
        },
        {
            "code": "21718003"
        },
        {
            "code": "21718004"
        },
        {
            "code": "21718005"
        },
        {
            "code": "21718006"
        },
        {
            "code": "21718007"
        },
        {
            "code": "21718008"
        },
        {
            "code": "21718009"
        },
        {
            "code": "21718010"
        },
        {
            "code": "21718011"
        },
        {
            "code": "21718012"
        },
        {
            "code": "21718013"
        },
        {
            "code": "21718014"
        },
        {
            "code": "21718015"
        },
        {
            "code": "21718016"
        },
        {
            "code": "21718017"
        },
        {
            "code": "21718018"
        },
        {
            "code": "21718019"
        },
        {
            "code": "21718020"
        },
        {
            "code": "21718021"
        },
        {
            "code": "21718022"
        },
        {
            "code": "21718023"
        },
        {
            "code": "21718024"
        },
        {
            "code": "21718025"
        },
        {
            "code": "21718026"
        },
        {
            "code": "21718027"
        },
        {
            "code": "21718028"
        },
        {
            "code": "21718029"
        },
        {
            "code": "21718030"
        },
        {
            "code": "21718031"
        },
        {
            "code": "21718032"
        },
        {
            "code": "21718034"
        },
        {
            "code": "21718035"
        },
        {
            "code": "21718036"
        },
        {
            "code": "21718037"
        },
        {
            "code": "21718038"
        },
        {
            "code": "21718039"
        },
        {
            "code": "21718040"
        },
        {
            "code": "21718041"
        },
        {
            "code": "21718042"
        },
        {
            "code": "21718043"
        },
        {
            "code": "21718044"
        },
        {
            "code": "21718045"
        },
        {
            "code": "21718046"
        }
    ]
}