{
    "code": "21715007",
    "name": "Química",
    "classes": [
        {
            "type": "A1",
            "events": [
                {
                    "date": "2025-02-12",
                    "start_hour": "16:30",
                    "end_hour": "18:00",
                    "location": "Aula B01"
                },
                {
                    "date": "2025-02-19",
                    "start_hour": "16:30",
                    "end_hour": "18:00",
                    "location": "Aula B01"
                },
                {
                    "date": "2025-02-26",
                    "start_hour": "16:30",
                    "end_hour": "18:00",
                    "location": "Aula B01"
                },
                {
                    "date": "2025-03-05",
                    "start_hour": "16:30",
                    "end_hour": "18:00",
                    "location": "Aula B01"
                },
                {
                    "date": "2025-03-12",
                    "start_hour": "16:30",
                    "end_hour": "18:00",
                    "location": "Aula B01"
                },
                {
                    "date": "2025-03-19",
                    "start_hour": "16:30",
                    "end_hour": "18:00",
                    "location": "Aula B01"
                },
                {
                    "date": "2025-03-26",
                    "start_hour": "16:30",
                    "end_hour": "18:00",
                    "location": "Aula B01"
                },
                {
                    "date": "2025-04-02",
                    "start_hour": "16:30",
                    "end_hour": "18:00",
                    "location": "Aula B01"
                },
                {
                    "date": "2025-04-09",
                    "start_hour": "16:30",
                    "end_hour": "18:00",
                    "location": "Aula B01"
                },
                {
                    "date": "2025-04-23",
                    "start_hour": "16:30",
                    "end_hour": "18:00",
                    "location": "Aula B01"
                },
                {
                    "date": "2025-04-30",
                    "start_hour": "16:30",
                    "end_hour": "18:00",
                    "location": "Aula B01"
                },
                {
                    "date": "2025-05-07",
                    "start_hour": "16:30",
                    "end_hour": "18:00",
                    "location": "Aula B01"
                },
                {
                    "date": "2025-05-14",
                    "start_hour": "16:30",
                    "end_hour": "18:00",
                    "location": "Aula B01"
                },
                {
                    "date": "2025-02-10",
                    "start_hour": "19:30",
                    "end_hour": "21:00",
                    "location": "Aula B01"
                },
                {
                    "date": "2025-02-17",
                    "start_hour": "19:30",
                    "end_hour": "21:00",
                    "location": "Aula B01"
                },
                {
                    "date": "2025-02-24",
                    "start_hour": "19:30",
                    "end_hour": "21:00",
                    "location": "Aula B01"
                },
                {
                    "date": "2025-03-03",
                    "start_hour": "19:30",
                    "end_hour": "21:00",
                    "location": "Aula B01"
                },
                {
                    "date": "2025-03-10",
                    "start_hour": "19:30",
                    "end_hour": "21:00",
                    "location": "Aula B01"
                },
                {
                    "date": "2025-03-17",
                    "start_hour": "19:30",
                    "end_hour": "21:00",
                    "location": "Aula B01"
                },
                {
                    "date": "2025-03-31",
                    "start_hour": "19:30",
                    "end_hour": "21:00",
                    "location": "Aula B01"
                },
                {
                    "date": "2025-04-07",
                    "start_hour": "19:30",
                    "end_hour": "21:00",
                    "location": "Aula B01"
                },
                {
                    "date": "2025-04-21",
                    "start_hour": "19:30",
                    "end_hour": "21:00",
                    "location": "Aula B01"
                },
                {
                    "date": "2025-04-28",
                    "start_hour": "19:30",
                    "end_hour": "21:00",
                    "location": "Aula B01"
                },
                {
                    "date": "2025-05-05",
                    "start_hour": "19:30",
                    "end_hour": "21:00",
                    "location": "Aula B01"
                },
                {
                    "date": "2025-05-12",
                    "start_hour": "19:30",
                    "end_hour": "21:00",
                    "location": "Aula B01"
                },
                {
                    "date": "2025-05-19",
                    "start_hour": "19:30",
                    "end_hour": "21:00",
                    "location": "Aula B01"
                },
                {
                    "date": "2025-05-26",
                    "start_hour": "19:30",
                    "end_hour": "21:00",
                    "location": "Aula B01"
                }
            ]
        },
        {
            "type": "B1",
            "events": [
                {
                    "date": "2025-03-11",
                    "start_hour": "15:00",
                    "end_hour": "16:00",
                    "location": "Aula E03"
                },
                {
                    "date": "2025-03-18",
                    "start_hour": "15:00",
                    "end_hour": "16:00",
                    "location": "Aula E03"
                },
                {
                    "date": "2025-03-25",
                    "start_hour": "15:00",
                    "end_hour": "16:00",
                    "location": "Aula E03"
                },
                {
                    "date": "2025-04-01",
                    "start_hour": "15:00",
                    "end_hour": "16:00",
                    "location": "Aula E03"
                },
                {
                    "date": "2025-04-08",
                    "start_hour": "15:00",
                    "end_hour": "16:00",
                    "location": "Aula E03"
                },
                {
                    "date": "2025-04-22",
                    "start_hour": "15:00",
                    "end_hour": "16:00",
                    "location": "Aula E03"
                },
                {
                    "date": "2025-04-29",
                    "start_hour": "15:00",
                    "end_hour": "16:00",
                    "location": "Aula E03"
                },
                {
                    "date": "2025-05-06",
                    "start_hour": "15:00",
                    "end_hour": "16:00",
                    "location": "Aula E03"
                },
                {
                    "date": "2025-05-13",
                    "start_hour": "15:00",
                    "end_hour": "16:00",
                    "location": "Aula E03"
                },
                {
                    "date": "2025-05-20",
                    "start_hour": "15:00",
                    "end_hour": "16:00",
                    "location": "Aula E03"
                }
            ]
        },
        {
            "type": "B2",
            "events": [
                {
                    "date": "2025-03-11",
                    "start_hour": "16:00",
                    "end_hour": "17:00",
                    "location": "Aula E05"
                },
                {
                    "date": "2025-03-18",
                    "start_hour": "16:00",
                    "end_hour": "17:00",
                    "location": "Aula E05"
                },
                {
                    "date": "2025-03-25",
                    "start_hour": "16:00",
                    "end_hour": "17:00",
                    "location": "Aula E05"
                },
                {
                    "date": "2025-04-01",
                    "start_hour": "16:00",
                    "end_hour": "17:00",
                    "location": "Aula E05"
                },
                {
                    "date": "2025-04-08",
                    "start_hour": "16:00",
                    "end_hour": "17:00",
                    "location": "Aula E05"
                },
                {
                    "date": "2025-04-22",
                    "start_hour": "16:00",
                    "end_hour": "17:00",
                    "location": "Aula E05"
                },
                {
                    "date": "2025-04-29",
                    "start_hour": "16:00",
                    "end_hour": "17:00",
                    "location": "Aula E05"
                },
                {
                    "date": "2025-05-06",
                    "start_hour": "16:00",
                    "end_hour": "17:00",
                    "location": "Aula E05"
                },
                {
                    "date": "2025-05-13",
                    "start_hour": "16:00",
                    "end_hour": "17:00",
                    "location": "Aula E05"
                },
                {
                    "date": "2025-05-20",
                    "start_hour": "16:00",
                    "end_hour": "17:00",
                    "location": "Aula E05"
                }
            ]
        },
        {
            "type": "D1",
            "events": [
                {
                    "date": "2025-03-06",
                    "start_hour": "19:00",
                    "end_hour": "21:00",
                    "location": "Aula B13"
                },
                {
                    "date": "2025-03-20",
                    "start_hour": "19:00",
                    "end_hour": "21:00",
                    "location": "Aula B13"
                },
                {
                    "date": "2025-04-03",
                    "start_hour": "19:00",
                    "end_hour": "21:00",
                    "location": "Aula B13"
                },
                {
                    "date": "2025-04-24",
                    "start_hour": "19:00",
                    "end_hour": "21:00",
                    "location": "Aula B13"
                },
                {
                    "date": "2025-05-15",
                    "start_hour": "19:00",
                    "end_hour": "21:00",
                    "location": "Aula B13"
                }
            ]
        },
        {
            "type": "D2",
            "events": [
                {
                    "date": "2025-03-06",
                    "start_hour": "15:00",
                    "end_hour": "17:00",
                    "location": "Aula B13"
                },
                {
                    "date": "2025-03-20",
                    "start_hour": "15:00",
                    "end_hour": "17:00",
                    "location": "Aula B13"
                },
                {
                    "date": "2025-04-03",
                    "start_hour": "15:00",
                    "end_hour": "17:00",
                    "location": "Aula B13"
                },
                {
                    "date": "2025-04-24",
                    "start_hour": "15:00",
                    "end_hour": "17:00",
                    "location": "Aula B13"
                },
                {
                    "date": "2025-05-15",
                    "start_hour": "15:00",
                    "end_hour": "17:00",
                    "location": "Aula B13"
                }
            ]
        },
        {
            "type": "D3",
            "events": [
                {
                    "date": "2025-03-06",
                    "start_hour": "17:00",
                    "end_hour": "19:00",
                    "location": "Aula B13"
                },
                {
                    "date": "2025-03-20",
                    "start_hour": "17:00",
                    "end_hour": "19:00",
                    "location": "Aula B13"
                },
                {
                    "date": "2025-04-03",
                    "start_hour": "17:00",
                    "end_hour": "19:00",
                    "location": "Aula B13"
                },
                {
                    "date": "2025-04-24",
                    "start_hour": "17:00",
                    "end_hour": "19:00",
                    "location": "Aula B13"
                },
                {
                    "date": "2025-05-15",
                    "start_hour": "17:00",
                    "end_hour": "19:00",
                    "location": "Aula B13"
                }
            ]
        }
    ]
}